{
    "2021": [
        {
            "id": "Flotilla",
            "date": "March 10, 2019",
            "title": "Flotilla In Space",
            "description": "Dope 3D Turn Based Space Battles.",
            "author": "Jeff Salisbury",
            "banner": "https://cdn.cloudflare.steamstatic.com/steam/apps/55000/capsule_616x353.jpg?t=1586734432",
            "tags": [
                "PC",
                "Space",
                "Turn Based"
            ]
        }
    ],
    "older": [
        {
            "id": "test",
            "date": "April 21, 2018",
            "title": "Test Markdown for Testing",
            "description": "This should be md header info",
            "author": "Jeff Salisbury",
            "banner": "https://www.wellplated.com/wp-content/uploads/2019/03/Ultimate-Breakfast-Tacos.jpg",
            "tags": [
                "PC",
                "Space",
                "Turn Based"
            ]
        }
    ]
}